basic_engine/__init__.py
basic_engine/basic_engine_min.py
src/__init__.py
src/basic_engine.py
src/basic_engine_min.py
basic_engine-1.0.0.dist-info/METADATA
basic_engine-1.0.0.dist-info/WHEEL
basic_engine-1.0.0.dist-info/top_level.txt
basic_engine-1.0.0.dist-info/RECORD
