Metadata-Version: 2.1
Name: basic-engine
Version: 1.0.0
Summary: Basic Engine for Grasshopper
Author: Spacewalk-tech
Author-email: aa@spacewalk.tech
Classifier: Programming Language :: Python :: 3
Classifier: License :: OSI Approved :: MIT License
Classifier: Operating System :: OS Independent
Requires-Python: >=3.9
Requires-Dist: numpy>=1.23.5
Requires-Dist: shapely>=1.8.5
